dpav/__init__.py
dpav/temp.py
dpav-0.0.1.dist-info/LICENSE
dpav-0.0.1.dist-info/METADATA
dpav-0.0.1.dist-info/WHEEL
dpav-0.0.1.dist-info/top_level.txt
dpav-0.0.1.dist-info/RECORD
